MANIFEST.in
README.md
requirements.txt
setup.cfg
setup.py
cas/__init__.py
cas/apps.py
cas/auth.py
cas/backends.py
cas/cache.py
cas/domain.py
cas/exceptions.py
cas/middleware.py
cas/models.py
cas/mq.py
cas/urls.py
cas/utils.py
cas/views.py
cas/migrations/0001_initial.py
cas/migrations/__init__.py
cas/tests/__init__.py
cas/tests/cas_tests.py
cas/tests/get_pgt.py
cas/tests/test_hac_mq/__init__.py
cas/tests/test_hac_mq/apps.py
cas/tests/test_hac_mq/factories.py
cas/tests/test_hac_mq/models.py
cas/tests/test_hac_mq/testHacMq.py
cas/tests/test_hac_mq/migrations/0001_initial.py
cas/tests/test_hac_mq/migrations/__init__.py
hyperscas2.egg-info/PKG-INFO
hyperscas2.egg-info/SOURCES.txt
hyperscas2.egg-info/dependency_links.txt
hyperscas2.egg-info/requires.txt
hyperscas2.egg-info/top_level.txt
hyperscas2.egg-info/zip-safe
migrations/__init__.py
tests/__init__.py
tests/test_deprecation.py
tests/test_middleware.py
tests/test_settings.py
tests/urls.py
tests/views.py