Metadata-Version: 1.2
Name: hyperscas2
Version: 0.0.1
Summary: Django Cas Client (inherited from django-cas)
Home-page: UNKNOWN
Author: drinksober
Author-email: drinksober@foxmail.com
Maintainer: drinksober
Maintainer-email: drinksober@foxmail.com
License: MIT
Keywords: django,cas
Platform: UNKNOWN
Classifier: Development Status :: 5 - Production/Stable
Classifier: Environment :: Console
Classifier: Intended Audience :: End Users/Desktop
Classifier: Natural Language :: English
Classifier: Operating System :: OS Independent
Classifier: Programming Language :: Python
Classifier: Topic :: Internet :: WWW/HTTP :: Dynamic Content :: CGI Tools/Libraries
Classifier: Topic :: Utilities
Classifier: License :: OSI Approved :: BSD License
